{
  "mode": "population",
  "population": {
    "n": 2,
    "mix": [
      {
        "arquetipo": "Preocupado",
        "count": 2,
        "comportamiento": "- Cuestiona las respuestas\n- Contrasta con documentos\n- Desconfía de respuestas \"demasiado redondas\"\n- Usa la IA con cautela",
        "necesidades": "- Trazabilidad a fuente\n- Explicación del razonamiento\n- Mensajes claros de límites\n- Refuerzo del uso responsable",
        "barreras": "- Miedo a alucinaciones\n- Falta de transparencia\n- Respuestas sin fuente\n- Errores puntuales que rompen la confianza"
      }
    ],
    "demografia": {
      "edad_min": 31,
      "edad_max": 50,
      "ratio_hombres": 0.5,
      "adopcion_tecnologica": "Early adopters – adoptan pronto cuando la tecnología ya es viable; suelen influir en otros.",
      "profesion": "Ingeniero"
    }
  }
}