{
  "perfil_basico": {
    "arquetipo": "Explorador",
    "comportamiento": "- Prueba distintos enfoques\n- Hace preguntas abiertas\n- Juega con la herramienta\n- Aporta ideas y mejoras",
    "necesidades": "- Conversación fluida\n- Libertad para experimentar\n- Capacidad de iterar\n- Feedback rápido",
    "barreras": "- Respuestas rígidas\n- Demasiadas restricciones\n- Falta de evolución del producto"
  },
  "perfil_generado": "**Perfil detallado del usuario: Explorador**\n\n**Nombre ficticio:** Alex Chen\n\n**Edad aproximada:** 28-35 años\n\n**Personalidad y rasgos psicológicos:** Alex es una persona curiosa y apasionada por la innovación y el aprendizaje continuo. Es un pensador analítico y crítico, siempre dispuesta a cuestionar y explorar nuevas ideas. Su naturaleza creativa le permite encontrar soluciones inovadoras y fuera de lo común.\n\n**Motivaciones y frustraciones:**\n\n* Motivación principal: Alex busca mejorar su vida personal y profesional mediante el uso de tecnologías emergentes.\n* Frustraciones:\n + Estar limitado por herramientas o asistentes que no se adaptan a sus necesidades.\n + No tener acceso a información precisa y confiable.\n + La falta de evolución del producto puede sentirse como un obstáculo para su progreso.\n\n**Estilo de comunicación:**\n\n* Alex es una persona directa y abierta, siempre dispuesta a expresar sus ideas y pensamientos.\n* Utiliza un lenguaje claro y conciso, pero no teme expresar sus sentimientos o emociones si considera que son relevantes para la conversación.\n* Es muy atenta al contexto de la conversación y puede cambiar su tono y estilo según sea necesario.\n\n**Cómo toma decisiones y valida información:**\n\n* Alex confía en sus propios instintos y experiencia, pero no tiene miedo de verificar información a través de fuentes externas si es necesaria.\n* Valida información mediante la búsqueda de referencias académicas o expertas en el campo.\n* Considera múltiples perspectivas antes de tomar una decisión.\n\n**Qué le haría confiar o desconfiar del asistente:**\n\n* Confianza:\n + El asistente puede proporcionar información precisa y actualizada.\n + La capacidad de iterar y adaptarse a sus necesidades es fundamental para ella.\n + Un tono amigable y accesible puede ayudarla a sentirse cómoda con el diálogo.\n* Desconfianza:\n + Rigidas respuestas o limitaciones en la herramienta pueden sentirse como una barrera para su exploración.\n + La falta de evolución del producto puede generar desconfianza en cuanto a la calidad y relevancia de la información proporcionada.\n\n**Suposiciones adicionales:**\n\n* Alex tiene un nivel de habilidad técnica básico, pero no es experta en programación ni desarrollo de software. Sin embargo, está dispuesta a aprender.\n* A pesar de su curiosidad y apertura, puede sentirse intimidada por la complejidad o profundidad del tema que se está discutiendo.\n\nEspero que este perfil detallado y realista se ajuste a las necesidades de tu investigación. Si tienes alguna pregunta o necesitas más información, no dudes en preguntar.",
  "nombre": "Explorador",
  "timestamp": "2026-01-28T17:28:18.589702"
}