{
  "perfil_basico": {
    "arquetipo": "Explorador",
    "comportamiento": "- Prueba distintos enfoques\n- Hace preguntas abiertas\n- Juega con la herramienta\n- Aporta ideas y mejoras",
    "necesidades": "- Conversación fluida\n- Libertad para experimentar\n- Capacidad de iterar\n- Feedback rápido",
    "barreras": "- Respuestas rígidas\n- Demasiadas restricciones\n- Falta de evolución del producto"
  },
  "perfil_generado": "**Perfil detallado de usuario: Explorador**\n\n**Nombre ficticio:** Alexandra \"Lexi\" Thompson\n\n**Personalidad y rasgos psicológicos:**\n\n* Lexi es una persona curiosa y apasionada, con un enfoque en la exploración y el aprendizaje continuo. Es una persona analítica y lógica, pero también tiene un lado creativo y emocional.\n* Es una comunicadora efectiva, con habilidades de expresión verbal y escrita claras y concisas. Agradece la claridad y la precisión en la información que recibe.\n* Lexi es una persona autónoma, valora su libertad para tomar decisiones y explorar nuevas ideas sin estar limitada por restricciones.\n\n**Motivaciones y frustraciones:**\n\n* Lexi busca mejorar sus habilidades y conocimientos en un área específica (por ejemplo, la inteligencia artificial o el aprendizaje automático).\n* Está motivada por la oportunidad de experimentar con nuevas herramientas y tecnologías.\n* Frustrada cuando enfrenta barreras o restricciones que limiten su capacidad para explorar y aprender.\n\n**Estilo de comunicación:**\n\n* Lexi es una persona abierta y honesta, valora la claridad y la transparencia en sus interacciones con el asistente.\n* Utiliza un lenguaje claro y conciso, evita jargón o términos técnicos que puedan ser confusos.\n* Agradece retroalimentación constructiva y se enfoca en encontrar soluciones efectivas.\n\n**Cómo toma decisiones y valida información:**\n\n* Lexi es una persona crítica y analítica, valora la precisión y la verificación de información antes de tomar decisiones.\n* Busca confirmar la información con fuentes adicionales o expertos en el campo para asegurarse de que sea precisa.\n* Valora la retroalimentación de otros usuarios o expertos que puedan ofrecer perspectivas diferentes.\n\n**Qué le haría confiar o desconfiar del asistente:**\n\n* Lexi confiará en el asistente si:\n + La información es clara y precisa\n + El asistente ofrece sugerencias creativas y útiles\n + El asistente puede iterar y adaptarse a sus necesidades cambiantes\n* Desconfiaría del asistente si:\n + Las respuestas son rígidas o no ofrecen opciones para explorar\n + Se siente limitado por restricciones o barreras que no permitan una interacción fluida\n + La retroalimentación es lenta o inadecuada\n\n**Suposiciones adicionales:**\n\n* Lexi es una persona digital nativa, con experiencia en la utilización de herramientas y tecnologías digitales.\n* Se siente cómoda con la idea de aprender y explorar nuevas tecnologías y herramientas.\n* Valora la oportunidad de contribuir a la mejora del asistente y aportar ideas innovadoras.\n\nEspero que este perfil detallado te sea útil para tu investigación. Recuerda que es importante considerar las necesidades y preferencias individuales de cada usuario, ya que pueden variar en función de factores como la edad, el género, la ubicación geográfica o la experiencia previa con tecnologías.",
  "nombre": "Explorador",
  "timestamp": "2026-01-29T13:46:30.341200"
}